[
    {
        "_id": { "$oid": "66a80857fa2621b9547dd650" },
        "image": "https://encrypted-tbn0.gstatic.com/images?q=tbn:ANd9GcSiJum2uhkyYLSOaJP0uZ_FDaz3OZBWlDCCUJirzAxn0Lu37yrP",
        "title": "Joba",
        "description": "Hibiscus rosa-sinensis, known colloquially ",
        "price": { "$numberInt": "20" },
        "category": {
            "image": "https://encrypted-tbn0.gstatic.com/images?q=tbn:ANd9GcSiJum2uhkyYLSOaJP0uZ_FDaz3OZBWlDCCUJirzAxn0Lu37yrP",
            "title": "Joba",
            "_id": { "$oid": "66a803196ff0e30207872cd1" },
            "__v": { "$numberInt": "0" }
        },
        "inventory": {
            "quantity": { "$numberInt": "11" },
            "inStock": true,
            "_id": { "$oid": "66a80857fa2621b9547dd652" }
        },
        "rating": { "$numberInt": "5" },
        "__v": { "$numberInt": "0" }
    },
    {
        "image": "https://t3.ftcdn.net/jpg/04/90/39/58/360_F_490395808_MLzc6oHe4WzgZ3vPcqnCNj0NlzAerQrP.jpg",
        "title": "Cycus",
        "description": "Hibiscus rosa-sinensis, known colloquially ",
        "price": { "$numberInt": "20" },
        "category": {
            "_id": { "$oid": "66c8e1ce7d2825cdb9b5b1e4" },
            "image": "https://t3.ftcdn.net/jpg/04/90/39/58/360_F_490395808_MLzc6oHe4WzgZ3vPcqnCNj0NlzAerQrP.jpg",
            "title": "Cycus",
            "__v": { "$numberInt": "0" }
        },
        "inventory": {
            "quantity": { "$numberInt": "11" },
            "inStock": true,
            "_id": { "$oid": "66a80857fa2621b9547dd652" }
        },
        "rating": { "$numberInt": "5" },
        "__v": { "$numberInt": "0" }
    }
]
